ogitm/__init__.py
ogitm/compat.py
ogitm/fields.py
ogitm-0.1.0.dist-info/DESCRIPTION.rst
ogitm-0.1.0.dist-info/top_level.txt
ogitm-0.1.0.dist-info/RECORD
ogitm-0.1.0.dist-info/METADATA
ogitm-0.1.0.dist-info/WHEEL
ogitm-0.1.0.dist-info/metadata.json
