Metadata-Version: 2.0
Name: ogitm
Version: 0.1.0
Summary: A OO-based Git Database
Home-page: https://github.com/MrJohz/ogitm
Author: Jonathan Frere
Author-email: UNKNOWN
License: MIT
Keywords: git database
Platform: UNKNOWN
Classifier: Development Status :: 3 - Alpha
Classifier: Intended Audience :: Developers
Classifier: License :: OSI Approved :: MIT License
Classifier: Programming Language :: Python :: 3 :: Only
Classifier: Programming Language :: Python :: 3.2
Classifier: Programming Language :: Python :: 3.3
Classifier: Programming Language :: Python :: 3.4
Classifier: Topic :: Database
Requires-Dist: pygit2 (==0.22.0)
Requires-Dist: inflection (==0.3.0)
Provides-Extra: dev
Requires-Dist: pytest (==2.6.4); extra == 'dev'
Requires-Dist: pytest-flakes (==0.2); extra == 'dev'
Requires-Dist: pytest-pep8 (==1.0.6); extra == 'dev'
Requires-Dist: pytest-cov (==1.8.1); extra == 'dev'
Requires-Dist: coverage (==3.7.1); extra == 'dev'
Requires-Dist: python-coveralls (==2.5.0); extra == 'dev'
Requires-Dist: Sphinx (==1.3.1); extra == 'dev'
Provides-Extra: rtd
Requires-Dist: inflection (==0.3.0); extra == 'rtd'
Requires-Dist: sphinxcontrib-napoleon; extra == 'rtd'
